TagCache-0.2.2.dist-info/DESCRIPTION.rst
TagCache-0.2.2.dist-info/METADATA
TagCache-0.2.2.dist-info/RECORD
TagCache-0.2.2.dist-info/WHEEL
TagCache-0.2.2.dist-info/metadata.json
TagCache-0.2.2.dist-info/top_level.txt
tagcache/__init__.py
tagcache/cache.py
tagcache/metadata.py
tagcache/serialize.py
tagcache/utils.py
