Metadata-Version: 2.0
Name: TagCache
Version: 0.2.2
Summary: A small file-based cache library with tag support.
Home-page: https://github.com/huangjunwen/tagcache
Author: Huang Junwen
Author-email: kassarar@gmail.com
License: MIT
Keywords: python cache tag file-based
Platform: UNKNOWN
Classifier: Programming Language :: Python :: 2
Classifier: Programming Language :: Python :: 2.7
Classifier: Topic :: Software Development :: Libraries
